buspasslib/__init__.py
buspasslib/message.py
buspasslib-0.1.0.dist-info/LICENSE
buspasslib-0.1.0.dist-info/METADATA
buspasslib-0.1.0.dist-info/WHEEL
buspasslib-0.1.0.dist-info/top_level.txt
buspasslib-0.1.0.dist-info/RECORD
