Metadata-Version: 2.2
Name: buspasslib
Version: 0.1.0
Summary: This is a simple Python package that prints the bus pass number of user.
Home-page: 
Author: Anusha-x23420065@student.ncirl.ie
Author-email: x23420065@student.ncirl.ie
Keywords: buspasslib
Classifier: Intended Audience :: Education
Classifier: Operating System :: Microsoft :: Windows :: Windows 10
Classifier: License :: OSI Approved :: MIT License
Classifier: Programming Language :: Python :: 3
Requires-Python: >=3.6
License-File: LICENSE
Dynamic: author
Dynamic: author-email
Dynamic: classifier
Dynamic: description
Dynamic: keywords
Dynamic: requires-python
Dynamic: summary
